{
  "version": "intel-v1.0.7",
  "release_date": "2025-11-06",
  "platforms": {
    "macos_silicon": {
      "version": "intel-v1.0.7",
      "download_url": "https://github.com/Carmel-Labs-Inc/fabric-downloads/releases/download/intel-v1.0.7/FabricAgent-Silicon-intel-v1.0.7.zip",
      "sha256": "",
      "size_bytes": 0,
      "min_os_version": "12.0"
    },
    "macos_intel": {
      "version": "intel-v1.0.7",
      "download_url": "https://github.com/Carmel-Labs-Inc/fabric-downloads/releases/download/intel-v1.0.7/FabricAgent-Intel-intel-v1.0.7.zip",
      "sha256": "2409df43b286a46d974f5ba8ce60c400d2a0591201b425c17daf1e743f8cc9f1",
      "size_bytes": 0,
      "min_os_version": "12.0"
    }
  },
  "release_notes": "https://github.com/Carmel-Labs-Inc/fabric-silicon/releases/tag/intel-v1.0.7",
  "changelog": [
    "intel-v1.0.7 - Production release",
    "- 28 fully implemented workloads (Compute, Data, Media, Inference, Training)",
    "- WebSocket real-time job notifications",
    "- Proof of Execution with privacy protection",
    "- Automatic model cache cleanup",
    "- Background daemon mode"
  ]
}
